auth_service_client/__init__.py
auth_service_client/client.py
usf_auth_service_client-0.0.17.dist-info/METADATA
usf_auth_service_client-0.0.17.dist-info/WHEEL
usf_auth_service_client-0.0.17.dist-info/top_level.txt
usf_auth_service_client-0.0.17.dist-info/RECORD
